atdata/.gitignore
atdata/__init__.py
atdata/_cid.py
atdata/_exceptions.py
atdata/_helpers.py
atdata/_hf_api.py
atdata/_logging.py
atdata/_protocols.py
atdata/_schema_codec.py
atdata/_sources.py
atdata/_stub_manager.py
atdata/_type_utils.py
atdata/dataset.py
atdata/lens.py
atdata/promote.py
atdata/repository.py
atdata/testing.py
atdata/atmosphere/__init__.py
atdata/atmosphere/_types.py
atdata/atmosphere/client.py
atdata/atmosphere/lens.py
atdata/atmosphere/records.py
atdata/atmosphere/schema.py
atdata/atmosphere/store.py
atdata/cli/__init__.py
atdata/cli/diagnose.py
atdata/cli/inspect.py
atdata/cli/local.py
atdata/cli/preview.py
atdata/cli/schema.py
atdata/local/__init__.py
atdata/local/_entry.py
atdata/local/_index.py
atdata/local/_repo_legacy.py
atdata/local/_s3.py
atdata/local/_schema.py
atdata/manifest/__init__.py
atdata/manifest/_aggregates.py
atdata/manifest/_builder.py
atdata/manifest/_fields.py
atdata/manifest/_manifest.py
atdata/manifest/_query.py
atdata/manifest/_writer.py
atdata/providers/__init__.py
atdata/providers/_base.py
atdata/providers/_factory.py
atdata/providers/_postgres.py
atdata/providers/_redis.py
atdata/providers/_sqlite.py
atdata-0.3.0b1.dist-info/METADATA
atdata-0.3.0b1.dist-info/WHEEL
atdata-0.3.0b1.dist-info/entry_points.txt
atdata-0.3.0b1.dist-info/licenses/LICENSE
atdata-0.3.0b1.dist-info/RECORD
