Metadata-Version: 2.4
Name: atdata
Version: 0.3.0b1
Summary: A loose federation of distributed, typed datasets
Author-email: Maxine Levesque <hello@maxine.science>, "Maxine @ Forecast Bio" <maxine@forecast.bio>
License-File: LICENSE
Requires-Python: >=3.12
Requires-Dist: atproto>=0.0.65
Requires-Dist: boto3>=1.41.5
Requires-Dist: fastparquet>=2024.11.0
Requires-Dist: libipld>=3.3.2
Requires-Dist: msgpack>=1.1.2
Requires-Dist: numpy>=2.3.4
Requires-Dist: ormsgpack>=1.11.0
Requires-Dist: pandas>=2.3.3
Requires-Dist: pydantic>=2.12.5
Requires-Dist: python-dotenv>=1.2.1
Requires-Dist: redis-om>=0.3.5
Requires-Dist: requests>=2.32.5
Requires-Dist: s3fs>=2025.12.0
Requires-Dist: schemamodels>=0.9.1
Requires-Dist: tqdm>=4.67.1
Requires-Dist: typer>=0.21.1
Requires-Dist: webdataset>=1.0.2
Provides-Extra: atmosphere
Requires-Dist: atproto>=0.0.55; extra == 'atmosphere'
Provides-Extra: postgres
Requires-Dist: psycopg[binary]>=3.1; extra == 'postgres'
